odoo8_addon_company_eori_number-8.0.1.0.0.99.dev4-py2.7-nspkg.pth
odoo8_addon_company_eori_number-8.0.1.0.0.99.dev4.dist-info/METADATA
odoo8_addon_company_eori_number-8.0.1.0.0.99.dev4.dist-info/RECORD
odoo8_addon_company_eori_number-8.0.1.0.0.99.dev4.dist-info/WHEEL
odoo8_addon_company_eori_number-8.0.1.0.0.99.dev4.dist-info/namespace_packages.txt
odoo8_addon_company_eori_number-8.0.1.0.0.99.dev4.dist-info/top_level.txt
odoo_addons/company_eori_number/README.rst
odoo_addons/company_eori_number/__init__.py
odoo_addons/company_eori_number/__openerp__.py
odoo_addons/company_eori_number/i18n/company_eori_number.pot
odoo_addons/company_eori_number/models/__init__.py
odoo_addons/company_eori_number/models/res_company.py
odoo_addons/company_eori_number/static/description/icon.png
odoo_addons/company_eori_number/views/res_company.xml
